asdf_pydantic/__init__.py
asdf_pydantic/__version__.py
asdf_pydantic/converter.py
asdf_pydantic/model.py
asdf_pydantic/examples/__init__.py
asdf_pydantic/examples/extensions.py
asdf_pydantic/examples/shapes.py
asdf_pydantic/examples/tree.py
asdf_pydantic-1.1.0.dist-info/METADATA
asdf_pydantic-1.1.0.dist-info/WHEEL
asdf_pydantic-1.1.0.dist-info/entry_points.txt
asdf_pydantic-1.1.0.dist-info/licenses/LICENSE
asdf_pydantic-1.1.0.dist-info/RECORD
