Metadata-Version: 2.3
Name: asdf-pydantic
Version: 1.1.0
Summary: Create ASDF tags with pydantic models
Project-URL: Documentation, https://asdf-pydantic.readthedocs.io
Project-URL: Issues, https://github.com/ketozhang/asdf-pydantic/issues
Project-URL: Source, https://github.com/ketozhang/asdf-pydantic
Author-email: "Keto D. Zhang" <keto.zhang@gmail.com>
License-File: LICENSE
Classifier: Development Status :: 4 - Beta
Classifier: Programming Language :: Python
Classifier: Programming Language :: Python :: 3.9
Classifier: Programming Language :: Python :: 3.10
Classifier: Programming Language :: Python :: 3.11
Classifier: Programming Language :: Python :: Implementation :: CPython
Classifier: Programming Language :: Python :: Implementation :: PyPy
Requires-Python: >=3.9
Requires-Dist: asdf>=2
Requires-Dist: pydantic<2,>=1
